ronto/__init__.py
ronto/main.py
ronto/cli/__init__.py
ronto/cli/bootstrap.py
ronto/cli/build.py
ronto/cli/docker.py
ronto/cli/fetch.py
ronto/cli/init.py
ronto/cli/publish.py
ronto/cli/run.py
ronto/data/git/cookiecutter.json
ronto/data/git/{{cookiecutter.project_slug}}/ronto.yml
ronto/data/git/{{cookiecutter.project_slug}}/site.conf
ronto/data/git-docker/cookiecutter.json
ronto/data/git-docker/{{cookiecutter.project_slug}}/ronto.yml
ronto/data/git-docker/{{cookiecutter.project_slug}}/site.conf
ronto/data/ignore/cookiecutter.json
ronto/data/ignore/{{cookiecutter.project_slug}}/ronto.yml
ronto/data/ignore/{{cookiecutter.project_slug}}/site.conf
ronto/data/ignore-docker/cookiecutter.json
ronto/data/ignore-docker/{{cookiecutter.project_slug}}/ronto.yml
ronto/data/ignore-docker/{{cookiecutter.project_slug}}/site.conf
ronto/data/repo/cookiecutter.json
ronto/data/repo/{{cookiecutter.project_slug}}/ronto.yml
ronto/data/repo/{{cookiecutter.project_slug}}/site.conf
ronto/data/repo-docker/cookiecutter.json
ronto/data/repo-docker/{{cookiecutter.project_slug}}/ronto.yml
ronto/data/repo-docker/{{cookiecutter.project_slug}}/site.conf
ronto/model/__init__.py
ronto/model/builder.py
ronto/model/docker.py
ronto/model/fetcher.py
ronto/model/init.py
ronto/model/publish.py
ronto-1.5.0.dist-info/METADATA
ronto-1.5.0.dist-info/WHEEL
ronto-1.5.0.dist-info/entry_points.txt
ronto-1.5.0.dist-info/top_level.txt
ronto-1.5.0.dist-info/RECORD
