Metadata-Version: 2.1
Name: ronto
Version: 1.5.0
Summary: Wrapper around building stuff using repotool and Yocto
Home-page: https://github.com/almedso/ronto
Author: Volker Kempert
Author-email: volker.kempert@almedso.de
Maintainer: Volker Kempert
Maintainer-email: volker.kempert@almedso.de
License: MIT license
Project-URL: Documentation, https://ronto.readthedocs.io
Project-URL: Bug Reports, https://github.com/almedso/ronto/issues
Project-URL: Source, https://github.com/almedso/ronto/
Keywords: ronto
Platform: UNKNOWN
Classifier: Development Status :: 3 - Alpha
Classifier: Intended Audience :: Developers
Classifier: Intended Audience :: Information Technology
Classifier: Topic :: Software Development :: Build Tools
Classifier: Topic :: Utilities
Classifier: Environment :: Console
Classifier: Programming Language :: Python :: 3.6
Requires-Dist: PyYAML (==5.3.1)
Requires-Dist: cookiecutter (==1.7.2)
Requires-Dist: docker (==4.2.0)
Requires-Dist: psutil (==5.7.0)
